{"is_source_file": false, "format": "", "description": "", "external_files": [], "external_methods": [], "published": [], "classes": [], "methods": [], "calls": [], "search-terms": [], "state": 2, "file_id": 39, "knowledge_revision": 80, "git_revision": "545bb7d77bfb7527a1c9f4c887a7d8385d1d942f", "hash": "a675cf9da75d8b5e530d17eaca6f2db3", "format-version": 4, "code-base-name": "finance_tracker_frontend", "filename": "finance_tracker_frontend/pubspec.yaml", "revision_history": [{"80": "545bb7d77bfb7527a1c9f4c887a7d8385d1d942f"}]}