{"is_source_file": false, "format": "", "description": "", "external_files": [], "external_methods": [], "published": [], "classes": [], "methods": [], "calls": [], "search-terms": [], "state": 2, "file_id": 31, "knowledge_revision": 64, "git_revision": "d18ecb07733f6b0e72917cf35151211801f4012e", "hash": "fe4c1b17910bcf2738bc7d4ed110d086", "format-version": 4, "code-base-name": "finance_tracker_frontend", "filename": "finance_tracker_frontend/pubspec.lock", "revision_history": [{"64": "d18ecb07733f6b0e72917cf35151211801f4012e"}]}